alo_pyai_sdk/__init__.py
alo_pyai_sdk/cli/__init__.py
alo_pyai_sdk/cli/configure.py
alo_pyai_sdk/cli/generate.py
alo_pyai_sdk/cli/main.py
alo_pyai_sdk/cli/provision_commands.py
alo_pyai_sdk/cli/registry_commands.py
alo_pyai_sdk/cli/run_commands.py
alo_pyai_sdk/core/__init__.py
alo_pyai_sdk/core/config_manager.py
alo_pyai_sdk/core/generator.py
alo_pyai_sdk/core/llm_loader.py
alo_pyai_sdk/core/registry_client.py
alo_pyai_sdk/templates/fastapi_agent/agent_definition.py.j2
alo_pyai_sdk/templates/fastapi_agent/config.py.j2
alo_pyai_sdk/templates/fastapi_agent/main.py.j2
alo_pyai_sdk/templates/fastapi_agent/tools.py.j2
alo_pyai_sdk/templates/fastapi_registry/__init__.py.j2
alo_pyai_sdk/templates/fastapi_registry/config.py.j2
alo_pyai_sdk/templates/fastapi_registry/main.py.j2
alo_pyai_sdk/templates/fastapi_registry/models.py.j2
alo_pyai_sdk/templates/mcp_client/client.py.j2
alo_pyai_sdk-0.2.9.dist-info/METADATA
alo_pyai_sdk-0.2.9.dist-info/WHEEL
alo_pyai_sdk-0.2.9.dist-info/entry_points.txt
alo_pyai_sdk-0.2.9.dist-info/licenses/LICENSE
alo_pyai_sdk-0.2.9.dist-info/RECORD
