Metadata-Version: 2.4
Name: alo_pyai_sdk
Version: 0.2.9
Summary: SDK to facilitate the creation of AI agentic applications using Pydantic-AI, A2A, and MCP.
Project-URL: Homepage, https://github.com/yourusername/alo_pyai_sdk
Project-URL: Repository, https://github.com/yourusername/alo_pyai_sdk
Author-email: Daniele Ligorio <dl@alomana.com>
License: MIT
License-File: LICENSE
Classifier: Development Status :: 3 - Alpha
Classifier: Intended Audience :: Developers
Classifier: License :: OSI Approved :: MIT License
Classifier: Programming Language :: Python :: 3
Classifier: Programming Language :: Python :: 3.10
Classifier: Programming Language :: Python :: 3.11
Classifier: Programming Language :: Python :: 3.12
Classifier: Topic :: Scientific/Engineering :: Artificial Intelligence
Classifier: Topic :: Software Development :: Libraries :: Application Frameworks
Requires-Python: >=3.10
Requires-Dist: fastapi>=0.100.0
Requires-Dist: httpx>=0.25.0
Requires-Dist: jinja2>=3.0
Requires-Dist: pydantic-ai>=0.0.47
Requires-Dist: pydantic>=2.0
Requires-Dist: pyyaml>=6.0
Requires-Dist: typer[all]>=0.9.0
Requires-Dist: uvicorn[standard]>=0.20.0
Provides-Extra: dev
Requires-Dist: mypy; extra == 'dev'
Requires-Dist: pytest; extra == 'dev'
Requires-Dist: pytest-asyncio; extra == 'dev'
Requires-Dist: ruff; extra == 'dev'
